MeMu/MeMu.py
MeMu/__init__.py
MeMu/bg.png
MeMu/emulator.py
MeMu/icon.ico
MeMu-2.1.4.dist-info/METADATA
MeMu-2.1.4.dist-info/WHEEL
MeMu-2.1.4.dist-info/top_level.txt
MeMu-2.1.4.dist-info/RECORD
