Metadata-Version: 2.1
Name: MeMu
Version: 2.1.4
Summary: This is a user interface for running pyboy emulator. To use,
Requires-Dist: customtkinter (>=5.1.3)
Requires-Dist: Pillow (>=9.4.0)
Requires-Dist: pyboy (>=1.6.6)
